main.py
setup.py
monoliht.egg-info/PKG-INFO
monoliht.egg-info/SOURCES.txt
monoliht.egg-info/dependency_links.txt
monoliht.egg-info/requires.txt
monoliht.egg-info/top_level.txt